manychat/__init__.py
manychat/api.py
manychat/fb/__init__.py
manychat/fb/page.py
manychat/fb/sending.py
manychat/fb/subscriber.py
manychat-1.0.1.dist-info/LICENSE
manychat-1.0.1.dist-info/METADATA
manychat-1.0.1.dist-info/WHEEL
manychat-1.0.1.dist-info/top_level.txt
manychat-1.0.1.dist-info/RECORD
