Metadata-Version: 2.1
Name: manychat
Version: 1.0.1
Summary: A Python package for ManyChat API.
Home-page: https://github.com/daiangan/manychat-python
Author: Daian Gan
Author-email: daian@ganmedia.com
License: UNKNOWN
Project-URL: Bug Tracker, https://github.com/daiangan/manychat-python/issues
Platform: UNKNOWN
Classifier: Programming Language :: Python :: 3
Classifier: License :: OSI Approved :: MIT License
Classifier: Operating System :: OS Independent
Requires-Python: >=3.6
License-File: LICENSE
Requires-Dist: requests
